sensor/2gforce.py
sensor/__init__.py
sensor/gforce.py
sensor/sensor_controller.py
sensor/sensor_data.py
sensor/sensor_data_context.py
sensor/sensor_device.py
sensor/sensor_profile.py
sensor/sensor_utils.py
sensor_sdk-0.0.37.dist-info/licenses/LICENSE.txt
sensor_sdk-0.0.37.dist-info/METADATA
sensor_sdk-0.0.37.dist-info/WHEEL
sensor_sdk-0.0.37.dist-info/top_level.txt
sensor_sdk-0.0.37.dist-info/zip-safe
sensor_sdk-0.0.37.dist-info/RECORD
