Metadata-Version: 2.4
Name: sensor-sdk
Version: 0.0.37
Summary: Python sdk for Synchroni
Home-page: https://github.com/oymotion/SynchroniSDKPython
Author: Martin Ye
Author-email: yecq_82@hotmail.com
Requires-Python: >=3.9.0
License-File: LICENSE.txt
Requires-Dist: numpy
Requires-Dist: setuptools
Requires-Dist: bleak
Dynamic: author
Dynamic: author-email
Dynamic: description
Dynamic: description-content-type
Dynamic: home-page
Dynamic: license-file
Dynamic: requires-dist
Dynamic: requires-python
Dynamic: summary
